imagipy/__init__.py
imagipy/colors.py
imagipy-0.1.0.dist-info/DESCRIPTION.rst
imagipy-0.1.0.dist-info/METADATA
imagipy-0.1.0.dist-info/RECORD
imagipy-0.1.0.dist-info/WHEEL
imagipy-0.1.0.dist-info/metadata.json
imagipy-0.1.0.dist-info/top_level.txt
