Metadata-Version: 2.0
Name: imagipy
Version: 0.1.0
Summary: Image handling
Home-page: https://imagipy.samireland.com
Author: Sam Ireland
Author-email: mail@samireland.com
License: MIT
Platform: UNKNOWN
Classifier: Development Status :: 4 - Beta
Classifier: Intended Audience :: Other Audience
Classifier: License :: OSI Approved :: MIT License
Classifier: Topic :: Communications
Classifier: Programming Language :: Python :: 3
Classifier: Programming Language :: Python :: 3.5
Classifier: Programming Language :: Python :: 3.6
